aenoxiccord/__init__.py
aenoxiccord/blacklist.py
aenoxiccord/bot.py
aenoxiccord/components.py
aenoxiccord/emb.py
aenoxiccord/enums.py
aenoxiccord/errors.py
aenoxiccord/logs.py
aenoxiccord/sql.py
aenoxiccord/times.py
aenoxiccord/utils.py
aenoxiccord/cogs/blacklist.py
aenoxiccord/cogs/help.py
aenoxiccord/cogs/status_changer.py
aenoxiccord/cogs/dpy/blacklist_setup.py
aenoxiccord/cogs/dpy/help_setup.py
aenoxiccord/cogs/dpy/status_changer_setup.py
aenoxiccord/cogs/pyc/blacklist_setup.py
aenoxiccord/cogs/pyc/help_setup.py
aenoxiccord/cogs/pyc/status_changer_setup.py
aenoxiccord/internal/__init__.py
aenoxiccord/internal/colors.py
aenoxiccord/internal/config.py
aenoxiccord/internal/embed_templates.py
aenoxiccord/internal/ready_style.py
aenoxiccord/internal/translation.py
aenoxiccord/internal/dc/__init__.py
aenoxiccord/internal/dc/dc_imports.py
aenoxiccord/internal/language/de.json
aenoxiccord/internal/language/en.json
aenoxiccord/internal/language/languages.py
aenoxiccord-0.5.3.dist-info/LICENSE
aenoxiccord-0.5.3.dist-info/METADATA
aenoxiccord-0.5.3.dist-info/WHEEL
aenoxiccord-0.5.3.dist-info/top_level.txt
aenoxiccord-0.5.3.dist-info/RECORD
